Metadata-Version: 2.1
Name: licensify
Version: 0.2.1
Summary: Utility to apply license headers to source code files
Home-page: https://github.com/Simmovation/licensify
Author: Simmovation Ltd
Author-email: info@simmovation.tech
License: BSD
Platform: any
Requires-Python: >=2.7,!=3.1.*,!=3.2.*,!=3.3.*,!=3.4.*,<4
Provides-Extra: publish
Provides-Extra: test
Provides-Extra: build
